{
  "data": [{
    "BlogID": "1",
    "title": "9月精選居家",
    "time": "2018 01-03",
    "quote": "『 總而言之，好清理是很大的優點，有木地板的質感，卻沒有木地板的缺點。』-ｄ粉#楊湉湉",
    "content": "　　湉湉是歐巴一開始在網路上跟大家見面的時候，就選擇使用歐巴佈置新家的使用者，在我們某篇教學影片有新朋友在疑問一些使用問題的時候，湉湉很熱情的與網友們分享新家的成果，當時大家看到真的是狠刷一波讚呢！ 現在我們就帶各位ｄ粉與新朋友來看看湉湉從選擇到親手打造的心路歷程吧（眨眼 -- 湉湉，當初為什麼會想鋪地板? 一直以來都想要住有木地板的房子。 年初搬家，無意中在fb看到歐巴地板，馬上被吸引。 那時，選擇歐巴地板的原因是什麼？ 因為台灣天氣潮濕，尤其是北部，歐巴地板防水又可水洗，完全不會有發霉難整理的麻煩，材質安全無毒，原本只是想鋪設小孩的遊戲區，因為促銷活動，連臥室客廳也一起鋪設。 鋪完前後家中改變最大的是？ 整個家的質感馬上提升好多，不再只是冷冰冰的磁磚，鋪設也非常方便，不需要上膠，直接靠牆擺好就不會滑動，跟老公兩個人不到一天就完成了。 真實接觸dHSHOP歐巴地板的第一個感覺是什麼？ 剛收到的時候，還有驚訝了一下，木紋是立體的耶！ 而且雖然地板本身可壓折卻不會有痕跡，地板正面其實是硬的，不會被寵物抓咬破壞，平常也很好清理。 朋友家人來作客，會問嗎？ 朋友來家裡都會問一下我們的地板是哪裡買的，感覺很不錯，比起傳統木地板，省了施工費，沒有木頭那種回音，拖地不會濕濕黏黏的， 「總而言之，好清理是很大的優點，有木地板的質感，卻沒有木地板的缺點。」 有沒有小故事讓湉湉你印象深刻？ 朋友最近也買房，一直心動想下手，我們直接拿一箱回去給他們試舖，想必不久後就可以在歐巴地板板上看到他們分享了吧！ - 看完湉湉新家親自選品．親手打造的過程， 如果你也想開始親手打造，捲起袖子 　一起改變生活吧：）"
  }, {
    "BlogID": "2",
    "name": "犬宇宙美容中心",
    "address": "桃園市楊梅區梅獅路二段94號",
    "opentime": "9AM-6PM (週三休息)",
    "description": "神人級的黃先生用人字型法將地板鋪的美美的!「耐磨抗抓」以及「零甲醛」的特性是開寵物spa館的黃先生選擇歐巴地板的主要原因，若是家中有養毛小孩的朋友，仍在考慮是否要購入歐巴地板可以帶著你們的毛小孩前往犬宇宙寵物美容spa館，幫毛小孩做spa順便體驗一下歐巴地板的驚人魅力！",
    "productImg1": "https://www.dhshop.tw/static/img/floor.c6f4498.jpg",
    "productName": "歐巴地板",
    "guesslike": [{ "stitle": "基督教門諾會松江教會", "simg": "https://www.dhshop.tw/Image/other/Case/教會/case2.png", "sid": "3" }, { "stitle": "初樂-TureLove", "simg": "https://www.dhshop.tw/Image/other/Case/初樂/case1.png", "sid": "5" }, { "stitle": "小人衣櫃", "simg": "https://www.dhshop.tw/Image/other/Case/小人衣櫃/case1.png", "sid": "4" }],
    "img": [{ "url": "https://www.dhshop.tw/Image/other/Case/犬宇宙/case1.png" }, { "url": "https://www.dhshop.tw/Image/other/Case/犬宇宙/case2.png" }, { "url": "https://www.dhshop.tw/Image/other/Case/犬宇宙/case3.png" }, { "url": "https://www.dhshop.tw/Image/other/Case/犬宇宙/case4.png" }]
  }]
}
